async_bgm_api/__init__.py
async_bgm_api/api.py
async_bgm_api/exceptions.py
async_bgm_api/models/__init__.py
async_bgm_api/models/subject.py
async_bgm_api-0.1.0.dist-info/WHEEL
async_bgm_api-0.1.0.dist-info/METADATA
async_bgm_api-0.1.0.dist-info/RECORD
