Metadata-Version: 2.1
Name: async-bgm-api
Version: 0.1.0
Summary: 
License: MIT
Author: Trim21
Author-email: i@trim21.me
Requires-Python: >=3.6.1,<4.0.0
Classifier: License :: OSI Approved :: MIT License
Classifier: Programming Language :: Python :: 3
Classifier: Programming Language :: Python :: 3.7
Classifier: Programming Language :: Python :: 3.8
Provides-Extra: docs
Requires-Dist: aiohttp (>=3.0.0,<4.0.0)
Requires-Dist: pydantic (>=1.2,<2.0)
Requires-Dist: sphinx (>=2.3.1,<3.0.0); extra == "docs"
Requires-Dist: sphinx_rtd_theme (==0.4.3); extra == "docs"
